nibabel-stubs/__init__.pyi
nibabel-stubs/affines.pyi
nibabel-stubs/orientations.pyi
nibabel-stubs/py.typed
nibabel_stubs-0.1.0.dist-info/licenses/LICENSE.md
nibabel_stubs-0.1.0.dist-info/METADATA
nibabel_stubs-0.1.0.dist-info/WHEEL
nibabel_stubs-0.1.0.dist-info/top_level.txt
nibabel_stubs-0.1.0.dist-info/RECORD
