Metadata-Version: 2.4
Name: nibabel-stubs
Version: 0.1.0
Summary: Type stubs for nibabel
Author-email: Joshua Hoeflich <josh@nudge.com>
License: Copyright <2025> <Joshua Hoeflich>
Project-URL: Homepage, https://github.com/joshnibabel/nibabel-stubs
Project-URL: Repository, https://github.com/joshnibabel/nibabel-stubs
Project-URL: Issues, https://github.com/joshnibabel/nibabel-stubs/issues
Keywords: nibabel,type stubs,typing,mypy
Classifier: Typing :: Typed
Requires-Python: >=3.7
License-File: LICENSE.md
Dynamic: license-file
